honeygain/__init__.py
honeygain/honeygain.py
honeygain-0.0.2.dist-info/METADATA
honeygain-0.0.2.dist-info/WHEEL
honeygain-0.0.2.dist-info/top_level.txt
honeygain-0.0.2.dist-info/RECORD
