Metadata-Version: 2.1
Name: honeygain
Version: 0.0.2
Summary: A python library to interact with the Honeygain API
Home-page: https://github.com/Woodie-07/honeygain.py
Author: Woodie
Requires-Dist: requests
